pardot_api_client-0.0.1.dist-info/metadata.json
pardot_api_client-0.0.1.dist-info/WHEEL
pardot_api_client-0.0.1.dist-info/RECORD
pardot_api_client-0.0.1.dist-info/METADATA
pardot_api_client-0.0.1.dist-info/DESCRIPTION.rst
pardot_api_client-0.0.1.dist-info/top_level.txt
pardot/__init__.py
pardot/resource.py
pardot/constants.py
pardot/api_docs_parser.py
pardot/client.py
pardot/tests/__init__.py
