Metadata-Version: 2.0
Name: pardot-api-client
Version: 0.0.1
Summary: Pardot API Client
Home-page: https://github.com/maxnaude/pardot-api-client
Author: Max Naude
Author-email: maxnaude@gmail.com
License: UNKNOWN
Platform: UNKNOWN
Classifier: Development Status :: 4 - Beta
Classifier: Intended Audience :: Developers
Classifier: License :: OSI Approved :: MIT License
Classifier: Operating System :: OS Independent
Classifier: Programming Language :: Python
Classifier: Topic :: Internet :: WWW/HTTP :: Site Management
Classifier: Topic :: Office/Business
Classifier: Topic :: Software Development :: Libraries :: Python Modules
Requires-Dist: hammock (==0.2.4)
Requires-Dist: pprintpp (==0.3.0)
Requires-Dist: six (==1.10.0)
